bepasty_cli
