Metadata-Version: 1.1
Name: bepasty-client-cli
Version: 0.3.0
Summary: Command Line Client for the Bepasty Pastebin
Home-page: https://github.com/bepasty/bepasty-client-cli
Author: Dennis Schmalacker
Author-email: github@progde.de
License: BSD 2-clause
Platform: UNKNOWN
Classifier: Development Status :: 3 - Alpha
Classifier: Environment :: Console
Classifier: License :: OSI Approved :: BSD License
Classifier: Programming Language :: Python :: 2.7
Classifier: Programming Language :: Python :: 3
Classifier: Topic :: Communications :: File Sharing
Classifier: Topic :: System :: Archiving :: Backup
